davinci_resolve_mcp/__init__.py
davinci_resolve_mcp/server.py
davinci_resolve_mcp-0.1.1.dist-info/licenses/LICENSE
davinci_resolve_mcp-0.1.1.dist-info/METADATA
davinci_resolve_mcp-0.1.1.dist-info/WHEEL
davinci_resolve_mcp-0.1.1.dist-info/entry_points.txt
davinci_resolve_mcp-0.1.1.dist-info/top_level.txt
davinci_resolve_mcp-0.1.1.dist-info/RECORD
