Metadata-Version: 2.4
Name: davinci-resolve-mcp
Version: 0.1.1
Summary: DaVinci Resolve integration through the Model Context Protocol
Author-email: DaVinci Resolve MCP Contributors <example@example.com>
License-Expression: MIT
Project-URL: homepage, https://github.com/filmcademy/davinci-resolve-mcp
Project-URL: repository, https://github.com/filmcademy/davinci-resolve-mcp
Classifier: Programming Language :: Python :: 3
Requires-Python: >=3.10
License-File: LICENSE
Requires-Dist: mcp[cli]>=1.3.0
Dynamic: license-file
